{
	"id": "msme-production-environment",
	"name": "MSME - Production",
	"values": [
		{
			"key": "base_url",
			"value": "https://mycfo.club/stori/api",
			"type": "default",
			"enabled": true
		},
		{
			"key": "api_key",
			"value": "stori_your_production_api_key_here",
			"type": "secret",
			"enabled": true
		},
		{
			"key": "application_id",
			"value": "1",
			"type": "default",
			"enabled": true
		},
		{
			"key": "gst_upload_id",
			"value": "1",
			"type": "default",
			"enabled": true
		},
		{
			"key": "director_pan",
			"value": "ABCDE1234F",
			"type": "default",
			"enabled": true
		},
		{
			"key": "gstin",
			"value": "29ABCDE1234F1Z5",
			"type": "default",
			"enabled": true
		}
	],
	"_postman_variable_scope": "environment"
}

